{
  "collapse-filter": false,
  "search": "",
  "showTags": true,
  "showAttachments": true,
  "hideUnresolved": false,
  "showOrphans": true,
  "collapse-color-groups": true,
  "colorGroups": [],
  "collapse-display": true,
  "showArrow": true,
  "textFadeMultiplier": 2,
  "nodeSizeMultiplier": 1.09149374919448,
  "lineSizeMultiplier": 1.67754865317696,
  "collapse-forces": false,
  "centerStrength": 0.48691841732182,
  "repelStrength": 20,
  "linkStrength": 0.51578811702539,
  "linkDistance": 30,
  "scale": 0.042697400238458416,
  "close": true
}